interopt/__init__.py
interopt/__main__.py
interopt/definition.py
interopt/parameter.py
interopt/search_space.py
interopt/study.py
interopt/runner/__init__.py
interopt/runner/model.py
interopt/runner/grpc_runner/__init__.py
interopt/runner/grpc_runner/config_service_pb2.py
interopt/runner/grpc_runner/config_service_pb2.pyi
interopt/runner/grpc_runner/config_service_pb2_grpc.py
interopt/runner/grpc_runner/main.py
interopt/runner/grpc_runner/server.py
interopt-0.2.1.dist-info/METADATA
interopt-0.2.1.dist-info/WHEEL
interopt-0.2.1.dist-info/top_level.txt
interopt-0.2.1.dist-info/RECORD
