Metadata-Version: 2.1
Name: interopt
Version: 0.2.1
Summary: An interoperability layer for black-box optimization
Author: Jacob Odgård Tørring
Author-email: jacob.torring@ntnu.no
License: LICENSE
Requires-Dist: pandas <=1.3.5
Requires-Dist: catboost <=1.2.2
Requires-Dist: grpcio <=1.60.1
Requires-Dist: grpcio-tools <=1.60.1
Requires-Dist: protobuf <=4.25.3
Requires-Dist: scikit-learn <=1.5.0
Requires-Dist: requests <=2.27.1
Requires-Dist: pydantic <=2.7.1
